common_qml/CMakeLists.txt
common_qml/__init__.py
common_qml/_version.py
common_qml/py.typed
common_qml/qml/CommonQml/Fonts/FontLoader.js
common_qml/qml/CommonQml/Fonts/qmldir
common_qml/qml/CommonQml/Fonts/fonts/Hack/Hack-Bold.ttf
common_qml/qml/CommonQml/Fonts/fonts/Hack/Hack-BoldItalic.ttf
common_qml/qml/CommonQml/Fonts/fonts/Hack/Hack-Italic.ttf
common_qml/qml/CommonQml/Fonts/fonts/Hack/Hack-Regular.ttf
common_qml/qml/CommonQml/Fonts/fonts/Hack/LICENSE
common_qml/qml/CommonQml/Helper/DebugArea.qml
common_qml/qml/CommonQml/Helper/qmldir
common_qml/qml/CommonQml/Icons/IconLoader.js
common_qml/qml/CommonQml/Icons/qmldir
common_qml/qml/CommonQml/Icons/imgs/material/LICENSE
common_qml/qml/CommonQml/Icons/imgs/material/directions_car.svg
common_qml/qml/CommonQml/Icons/imgs/material/file_copy.svg
common_qml/qml/CommonQml/Icons/imgs/material/file_copy_all.svg
common_qml/qml/CommonQml/Icons/imgs/material/file_copy_png.svg
common_qml/qml/CommonQml/Icons/imgs/material/file_copy_svg.svg
common_qml/qml/CommonQml/Icons/imgs/material/folder_open.svg
common_qml/qml/CommonQml/Icons/imgs/material/home.svg
common_qml/qml/CommonQml/Icons/imgs/material/radio_button_checked.svg
common_qml/qml/CommonQml/Icons/imgs/material/save_as.svg
common_qml/qml/CommonQml/Icons/imgs/material/settings.svg
common_qml/qml/CommonQml/Icons/imgs/twyleg/LICENSE
common_qml/qml/CommonQml/Icons/imgs/twyleg/dev.svg
common_qml/qml/CommonQml/Icons/imgs/twyleg/rotation_loading.svg
common_qml/qml/CommonQml/Icons/imgs/twyleg/rotation_loading_large.svg
common_qml/qml/CommonQml/Items/DoubleSpinBox.qml
common_qml/qml/CommonQml/Items/FileFolderSelector.qml
common_qml/qml/CommonQml/Items/RotatingLoadingScreen.qml
common_qml/qml/CommonQml/Items/SliderSpinBox.qml
common_qml/qml/CommonQml/Items/SliderSpinBoxFading.qml
common_qml/qml/CommonQml/Items/SliderSpinBoxHighlightedBackground.qml
common_qml/qml/CommonQml/Items/Svg.qml
common_qml/qml/CommonQml/Items/qmldir
common_qml/qml/CommonQml/SidebarApp/NavigationSidebar.qml
common_qml-0.1.2.dist-info/LICENSE
common_qml-0.1.2.dist-info/METADATA
common_qml-0.1.2.dist-info/WHEEL
common_qml-0.1.2.dist-info/top_level.txt
common_qml-0.1.2.dist-info/RECORD
