Metadata-Version: 2.1
Name: common_qml
Version: 0.1.2
Summary: Common QML modules.
Home-page: https://github.com/twyleg/common_qml
Author: Torsten Wylegala
Author-email: mail@twyleg.de
License: GPL 3.0
Keywords: Qt QML common modules
License-File: LICENSE
Requires-Dist: pyside6
